lariat/__init__.py
lariat/lariat.py
lariat-0.2.0.dist-info/LICENSE
lariat-0.2.0.dist-info/METADATA
lariat-0.2.0.dist-info/WHEEL
lariat-0.2.0.dist-info/entry_points.txt
lariat-0.2.0.dist-info/top_level.txt
lariat-0.2.0.dist-info/RECORD
