Metadata-Version: 2.1
Name: lariat
Version: 0.2.0
Summary: Python utility for interfacing with the Device Farmer API
Author: Zetier
Project-URL: Homepage, https://github.com/Zetier/lariat
Project-URL: Bug Tracker, https://github.com/Zetier/lariat/issues
Keywords: lariat,devicefarmer,stf,automation,android,testing,openstf
Classifier: Intended Audience :: Developers
Classifier: License :: OSI Approved :: GNU General Public License v2 (GPLv2)
Classifier: Natural Language :: English
Classifier: Programming Language :: Python :: 3.8
Requires-Python: >=3.8
License-File: LICENSE
Requires-Dist: bravado ==11.0.*
Requires-Dist: adb-shell ==0.4.*
Requires-Dist: types-urllib3 ==1.26.*
